keycrate/__init__.py
keycrate/client.py
keycrate/utils.py
keycrate-0.1.0.dist-info/licenses/LICENSE
keycrate-0.1.0.dist-info/METADATA
keycrate-0.1.0.dist-info/WHEEL
keycrate-0.1.0.dist-info/top_level.txt
keycrate-0.1.0.dist-info/RECORD
