Metadata-Version: 2.4
Name: keycrate
Version: 0.1.0
Summary: Simple Keycrate license authentication SDK
Home-page: https://github.com/keycrate/keycrate-sdk/sdks/python
Author: keycrate
Requires-Python: >=3.8
License-File: LICENSE
Requires-Dist: requests>=2.0.0
Requires-Dist: hwid>=0.1.0
Dynamic: author
Dynamic: home-page
Dynamic: license-file
Dynamic: requires-dist
Dynamic: requires-python
Dynamic: summary
